ForMoSA/__init__.py
ForMoSA/main.py
ForMoSA/main_utilities.py
ForMoSA/adapt/__init__.py
ForMoSA/adapt/adapt_grid.py
ForMoSA/adapt/adapt_obs_mod.py
ForMoSA/adapt/extraction_functions.py
ForMoSA/nested_sampling/__init__.py
ForMoSA/nested_sampling/nested_logL_functions.py
ForMoSA/nested_sampling/nested_modif_spec.py
ForMoSA/nested_sampling/nested_prior_function.py
ForMoSA/nested_sampling/nested_sampling.py
ForMoSA/plotting/__init__.py
ForMoSA/plotting/plotting_class.py
ForMoSA-2.0.0.dist-info/LICENSE
ForMoSA-2.0.0.dist-info/METADATA
ForMoSA-2.0.0.dist-info/WHEEL
ForMoSA-2.0.0.dist-info/top_level.txt
ForMoSA-2.0.0.dist-info/RECORD
